datatrails_receipt_scitt/__init__.py
datatrails_receipt_scitt/attribute_decoder.py
datatrails_receipt_scitt/elementmetadata.py
datatrails_receipt_scitt/ethproofs.py
datatrails_receipt_scitt/exceptions.py
datatrails_receipt_scitt/khipureceipt.py
datatrails_receipt_scitt/namedproofs.py
datatrails_receipt_scitt/receipt.py
datatrails_receipt_scitt/receiptdecoder.py
datatrails_receipt_scitt/simplehashreceipt.py
datatrails_receipt_scitt/trie_alg.py
datatrails_receipt_scitt/v1.py
datatrails_receipt_scitt-0.5.0a0.dist-info/LICENSE
datatrails_receipt_scitt-0.5.0a0.dist-info/METADATA
datatrails_receipt_scitt-0.5.0a0.dist-info/WHEEL
datatrails_receipt_scitt-0.5.0a0.dist-info/entry_points.txt
datatrails_receipt_scitt-0.5.0a0.dist-info/top_level.txt
datatrails_receipt_scitt-0.5.0a0.dist-info/RECORD
