Metadata-Version: 2.1
Name: datatrails-receipt-scitt
Version: 0.5.0a0
Summary: Datatrails Scitt Receipt Verification in python
Home-page: https://github.com/datatrails/datatrails-receipt-scitt
Author: DataTrails Inc.
Author-email: support@datatrails.ai
License: MIT
Project-URL: Source, https://github.com/datatrails/datatrails-receipt-scitt
Project-URL: Tracker, https://github.com/datatrail/datatrails-receipt-scitt/issues
Classifier: Development Status :: 4 - Beta
Classifier: Environment :: Console
Classifier: Intended Audience :: Developers
Classifier: License :: OSI Approved :: MIT License
Classifier: Operating System :: POSIX :: Linux
Classifier: Programming Language :: Python :: 3.7
Classifier: Topic :: Utilities
Requires-Python: >=3.7
License-File: LICENSE
Requires-Dist: trie ~=2.1.0
Requires-Dist: pycose ~=1.0.1
Requires-Dist: cbor2 ~=5.4.6
Requires-Dist: rfc3339 ~=6.2
Requires-Dist: eth-hash[pycryptodome] ~=0.5.1
